LICENSE
MANIFEST.in
README.txt
setup.py
easymlserver/__init__.py
easymlserver/itemRecommender.py
easymlserver/server.py
easymlserver/topic_classifier.py
easymlserver.egg-info/PKG-INFO
easymlserver.egg-info/SOURCES.txt
easymlserver.egg-info/dependency_links.txt
easymlserver.egg-info/entry_points.txt
easymlserver.egg-info/requires.txt
easymlserver.egg-info/top_level.txt