Metadata-Version: 1.1
Name: easymlserver
Version: 0.1.2
Summary: Server package for EasyML-lib (Android machine learning)
Home-page: https://github.com/delvv/easyML-lib
Author: Delvv, Inc.
Author-email: info@delvv.com
License: Modified BSD
Download-URL: https://github.com/delvv/easyML-lib/archive/0.1.zip
Platform: any
Classifier: Programming Language :: Python
Classifier: Programming Language :: Python :: 2
Classifier: Operating System :: OS Independent
Classifier: Development Status :: 1 - Planning
Classifier: Environment :: Console
Classifier: Intended Audience :: Science/Research
